<?xml version="1.0" encoding="utf-8"?>
<Items>
  <Item name="Modular Backpack + Ammocrate + Shell Rack" identifier="MBAmmocrateShellRack" category="Equipment" tags="MBMOD,mountableweapon" fireproof="true" waterproof="true" cargocontaineridentifier="metalcrate" scale="0.5" impactsoundtag="impact_soft" description="">
    <Deconstruct time="40">
      <Item identifier="modularbackpack" amount="1" />
      <Item identifier="aluminium" amount="8" />
      <Item identifier="steel" amount="4" />
    </Deconstruct>
    <Fabricate suitablefabricators="fabricator" requiredtime="5">
      <RequiredItem identifier="modularbackpack" amount="1" />
      <RequiredItem identifier="aluminium" amount="8" />
      <RequiredItem identifier="steel" amount="4" />
    </Fabricate>
    <InventoryIcon texture="%ModDir%/MB + Ammocrate + Shell Rack/MB + Ammocrate + Shell Rack - On Back.png" sourcerect="0,0,232,259" />
    <Sprite texture="%ModDir%/MB + Ammocrate + Shell Rack/MB + Ammocrate + Shell Rack - Dropped.png" sourcerect="0,0,259,168" depth="0.6" origin="0.5,0.5" />
    <Body width="259" height="168" density="10" />
    <Wearable slots="Bag" msg="ItemMsgPickUpSelect">
      <sprite name="Backpack on character" texture="%ModDir%/MB + Ammocrate + Shell Rack/MB + Ammocrate + Shell Rack - On Back.png" limb="Torso" depth="0.8" hidelimb="false" canbehiddenbyotherwearables="false" inherittexturescale="true" origin="0.86,0.50" sourcerect="0,0,232,259" />
      <ItemContainer capacity="3" slotsperrow="3" hideitems="true">
        <Containable items="smallitem,weapon,gun" excludeditems="crate,toolbox,cargoscooter,backpack,MBMOD,mountableweapon" />
        <SlotIcon slotindex="3" texture="%ModDir%/Icons/Ammocrate.png" origin="0.5,0.5" />
        <SlotIcon slotindex="4" texture="%ModDir%/Icons/Ammocrate.png" origin="0.5,0.5" />
        <SlotIcon slotindex="5" texture="%ModDir%/Icons/Ammocrate.png" origin="0.5,0.5" />
        <SlotIcon slotindex="6" texture="%ModDir%/Icons/Ammocrate.png" origin="0.5,0.5" />
        <SlotIcon slotindex="7" texture="%ModDir%/Icons/Ammocrate.png" origin="0.5,0.5" />
        <SlotIcon slotindex="8" texture="%ModDir%/Icons/Ammocrate.png" origin="0.5,0.5" />
        <SubContainer capacity="6" maxstacksize="64">
          <Containable items="ammobox" excludeditems="MBMOD" />
        </SubContainer>
        <SlotIcon slotindex="9" texture="%ModDir%/Icons/Shell Rack.png" origin="0.5,0.5" />
        <SlotIcon slotindex="10" texture="%ModDir%/Icons/Shell Rack.png" origin="0.5,0.5" />
        <SlotIcon slotindex="11" texture="%ModDir%/Icons/Shell Rack.png" origin="0.5,0.5" />
        <SubContainer capacity="3" maxstacksize="64">
          <Containable items="railgunammo" excludeditems="MBMOD" />
        </SubContainer>
      </ItemContainer>
      <!-- WEIGHT SYSTEM -->
      <StatusEffect type="Always" target="Character">
        <RequiredItem item="smallitem,weapon,gun" type="Contained" targetslot="0" />
        <Affliction identifier="weight" amount="1" />
      </StatusEffect>
      <StatusEffect type="Always" target="Character">
        <RequiredItem item="smallitem,weapon,gun" type="Contained" targetslot="1" />
        <Affliction identifier="weight" amount="1" />
      </StatusEffect>
      <StatusEffect type="Always" target="Character">
        <RequiredItem item="smallitem,weapon,gun" type="Contained" targetslot="2" />
        <Affliction identifier="weight" amount="1" />
      </StatusEffect>
      <StatusEffect type="Always" target="Character">
        <RequiredItem item="smallitem,weapon,gun,ammobox,railgunammo" type="Contained" targetslot="3" />
        <Affliction identifier="weight" amount="2" />
      </StatusEffect>
      <StatusEffect type="Always" target="Character">
        <RequiredItem item="smallitem,weapon,gun,ammobox,railgunammo" type="Contained" targetslot="4" />
        <Affliction identifier="weight" amount="2" />
      </StatusEffect>
      <StatusEffect type="Always" target="Character">
        <RequiredItem item="smallitem,weapon,gun,ammobox,railgunammo" type="Contained" targetslot="5" />
        <Affliction identifier="weight" amount="2" />
      </StatusEffect>
      <StatusEffect type="Always" target="Character">
        <RequiredItem item="smallitem,weapon,gun,ammobox,railgunammo" type="Contained" targetslot="6" />
        <Affliction identifier="weight" amount="2" />
      </StatusEffect>
      <StatusEffect type="Always" target="Character">
        <RequiredItem item="smallitem,weapon,gun,ammobox,railgunammo" type="Contained" targetslot="7" />
        <Affliction identifier="weight" amount="2" />
      </StatusEffect>
      <StatusEffect type="Always" target="Character">
        <RequiredItem item="smallitem,weapon,gun,ammobox,railgunammo" type="Contained" targetslot="8" />
        <Affliction identifier="weight" amount="2" />
      </StatusEffect>
      <StatusEffect type="Always" target="Character">
        <RequiredItem item="smallitem,weapon,gun,railgunammo" type="Contained" targetslot="9" />
        <Affliction identifier="weight" amount="2" />
      </StatusEffect>
      <StatusEffect type="Always" target="Character">
        <RequiredItem item="smallitem,weapon,gun,railgunammo" type="Contained" targetslot="10" />
        <Affliction identifier="weight" amount="2" />
      </StatusEffect>
      <StatusEffect type="Always" target="Character">
        <RequiredItem item="smallitem,weapon,gun,railgunammo" type="Contained" targetslot="11" />
        <Affliction identifier="weight" amount="2" />
      </StatusEffect>
      <StatusEffect type="Always" target="Character">
        <RequiredItem item="smallitem,weapon,gun,railgunammo" type="Contained" targetslot="12" />
        <Affliction identifier="weight" amount="2" />
      </StatusEffect>
      <StatusEffect type="Always" target="Character">
        <RequiredItem item="smallitem,weapon,gun,railgunammo" type="Contained" targetslot="13" />
        <Affliction identifier="weight" amount="2" />
      </StatusEffect>
      <StatusEffect type="Always" target="Character">
        <RequiredItem item="smallitem,weapon,gun,railgunammo" type="Contained" targetslot="14" />
        <Affliction identifier="weight" amount="1" />
      </StatusEffect>
      <StatusEffect type="Always" target="Character">
        <RequiredItem item="smallitem,weapon,gun,railgunammo" type="Contained" targetslot="15" />
        <Affliction identifier="weight" amount="1" />
      </StatusEffect>
      <!-- SPECIFIC BONUS -->
      <SkillModifier skillidentifier="electrical" skillvalue="-20" />
      <SkillModifier skillidentifier="helm" skillvalue="-35" />
      <SkillModifier skillidentifier="mechanical" skillvalue="-20" />
      <SkillModifier skillidentifier="medical" skillvalue="-25" />
      <SkillModifier skillidentifier="weapons" skillvalue="-35" />
      <StatValue stattype="SwimmingSpeed" value="-0.50" />
      <StatValue stattype="WalkingSpeed" value="-0.15" />
      <StatValue stattype="RepairSpeed" value="-0.60" />
    </Wearable>
    <Holdable slots="RightHand,LeftHand" controlpose="true" holdpos="10,-90" handle1="0,60" msg="ItemMsgPickUpUse" canbeselected="false" canbepicked="true" pickkey="Use" />
  </Item>
</Items>